bayesbeat/__init__.py
bayesbeat/analysis.py
bayesbeat/conversion.py
bayesbeat/data.py
bayesbeat/filter.py
bayesbeat/plot.py
bayesbeat/priors.py
bayesbeat/result.py
bayesbeat/utils.py
bayesbeat/cli/__init__.py
bayesbeat/cli/build.py
bayesbeat/cli/config.py
bayesbeat/cli/generate.py
bayesbeat/cli/plot.py
bayesbeat/cli/priors.py
bayesbeat/cli/run.py
bayesbeat/config/__init__.py
bayesbeat/config/config.py
bayesbeat/config/default.ini
bayesbeat/config/htcondor.ini
bayesbeat/config/slurm.ini
bayesbeat/equations/General_Equation_1_Terms.txt
bayesbeat/equations/General_Equation_2_Terms.txt
bayesbeat/equations/General_Equation_3_Terms.txt
bayesbeat/equations/General_Equation_4_Terms.txt
bayesbeat/equations/General_Equation_5_Terms.txt
bayesbeat/equations/General_Equation_6_Terms.txt
bayesbeat/equations/General_Equation_7_Terms.txt
bayesbeat/equations/__init__.py
bayesbeat/equations/coefficients.py
bayesbeat/equations/functions.py
bayesbeat/model/__init__.py
bayesbeat/model/base.py
bayesbeat/model/beam.py
bayesbeat/model/generic_analytic.py
bayesbeat/model/simple.py
bayesbeat/model/utils.py
bayesbeat/reparameterisations/__init__.py
bayesbeat/reparameterisations/amplitude.py
bayesbeat/submit/__init__.py
bayesbeat/submit/condor.py
bayesbeat/submit/slurm.py
bayesbeat-0.1.0.dist-info/licenses/LICENSE.md
bayesbeat-0.1.0.dist-info/METADATA
bayesbeat-0.1.0.dist-info/WHEEL
bayesbeat-0.1.0.dist-info/entry_points.txt
bayesbeat-0.1.0.dist-info/top_level.txt
bayesbeat-0.1.0.dist-info/RECORD
