Metadata-Version: 2.4
Name: bayesbeat
Version: 0.1.0
Summary: Bayesian inference for two decaying beating signals
Author-email: "Michael J. Williams" <michaeljw1@googlemail.com>, "Simon C. Tait" <stait@caltech.edu>, Joseph Bayley <joseph.bayley@glasgow.ac.uk>, Bryan Barr <bryan.barr@glasgow.ac.uk>
License: MIT
Classifier: Programming Language :: Python :: 3
Requires-Python: >=3.8
License-File: LICENSE.md
Requires-Dist: click
Requires-Dist: hdf5storage
Requires-Dist: nessai>=0.8
Requires-Dist: corner
Requires-Dist: dill
Requires-Dist: sympy
Requires-Dist: h5py
Requires-Dist: seaborn
Requires-Dist: scipy
Requires-Dist: click
Provides-Extra: numba
Requires-Dist: numba; extra == "numba"
Provides-Extra: condor
Requires-Dist: pycondor; extra == "condor"
Provides-Extra: slurm
Requires-Dist: simple-slurm; extra == "slurm"
Provides-Extra: dev
Requires-Dist: pytest; extra == "dev"
Requires-Dist: numba; extra == "dev"
Dynamic: license-file
